setups/__init__.py
setups/cli.py
setups/help.py
test/__init__.py
setups-0.0.2.dist-info/LICENSE
setups-0.0.2.dist-info/METADATA
setups-0.0.2.dist-info/WHEEL
setups-0.0.2.dist-info/entry_points.txt
setups-0.0.2.dist-info/top_level.txt
setups-0.0.2.dist-info/RECORD
