Metadata-Version: 2.1
Name: setups
Version: 0.0.2
Summary: Setups: Dynamically generate setup.py for Python projects.
Home-page: https://github.com/muhammad-fiaz/setups-python
Author: Muhammad Fiaz
Author-email: contact@muhammadfiaz.com
License: MIT
Project-URL: Source Code, https://github.com/muhammad-fiaz/setups-python
Project-URL: Bug Tracker, https://github.com/muhammad-fiaz/setups-python/issues
Project-URL: Documentation, https://github.com/muhammad-fiaz/setups-python#readme
Classifier: Development Status :: 3 - Alpha
Classifier: Intended Audience :: Developers
Classifier: Programming Language :: Python :: 3
Classifier: License :: OSI Approved :: MIT License
Classifier: Operating System :: OS Independent
Requires-Python: >=3.6
License-File: LICENSE
Requires-Dist: click
Requires-Dist: setuptools
Requires-Dist: twine
Requires-Dist: wheel
Provides-Extra: tests
Requires-Dist: pytest ; extra == 'tests'
